<?xml version="1.0" encoding="UTF-8" standalone="yes"?>

<GameElements>
	<start>
		<worker>6</worker>
		<gold>50</gold>
		<wood>0</wood>
		<home>4</home>
	</start>
	<upgrade>
		<tree>
			<treeName>SoldierUpgrade</treeName>
			<type>
				<name>Health</name>
				<upgradeNode>
					<parent>Health</parent>
					<nodeName>Weapon1</nodeName>
					<object>Health</object>
					<value>30</value>
					<resourceCostType>Resource</resourceCostType>
					<resourceAmount>50</resourceAmount>
				</upgradeNode>
				<upgradeNode>
					<parent>Weapon1</parent>
					<nodeName>Weapon</nodeName>
					<object>Health</object>
					<value>50</value>
					<resourceCostType>Resource</resourceCostType>
					<resourceAmount>80</resourceAmount>
				</upgradeNode>
			</type>
			<type>
				<name>Attack</name>
				<upgradeNode>
					<parent>Attack</parent>
					<nodeName>RangeWeapon1</nodeName>
					<object>Range</object>
					<value>30</value>
					<resourceCostType>Resource</resourceCostType>
					<resourceAmount>50</resourceAmount>
				</upgradeNode>
				<upgradeNode>
					<parent>RangeWeapon1</parent>
					<nodeName>DamageWeapon1</nodeName>
					<object>Damage</object>
					<value>50</value>
					<resourceCostType>Resource</resourceCostType>
					<resourceAmount>80</resourceAmount>
				</upgradeNode>
			</type>
		</tree>
		<tree>
			<treeName>RegularUpgrade</treeName>
			<type>
				<name>Health</name>
				<upgradeNode>
					<parent>Health</parent>
					<nodeName>Weapon1</nodeName>
					<object>Health</object>
					<value>30</value>
					<resourceCostType>Resource</resourceCostType>
					<resourceAmount>50</resourceAmount>
				</upgradeNode>
				<upgradeNode>
					<parent>Weapon1</parent>
					<nodeName>Weapon</nodeName>
					<object>Health</object>
					<value>50</value>
					<resourceCostType>Resource</resourceCostType>
					<resourceAmount>80</resourceAmount>
				</upgradeNode>
			</type>
			<type>
				<name>Attack</name>
				<upgradeNode>
					<parent>Attack</parent>
					<nodeName>CanAttack</nodeName>
					<object>AttackStrategy</object>
					<value>0</value>
					<resourceCostType>Resource</resourceCostType>
					<resourceAmount>50</resourceAmount>
				</upgradeNode>
				<upgradeNode>
					<parent>Attack</parent>
					<nodeName>RangeWeapon1</nodeName>
					<object>Range</object>
					<value>50</value>
					<resourceCostType>Resource</resourceCostType>
					<resourceAmount>80</resourceAmount>
				</upgradeNode>
				<upgradeNode>
					<parent>Attack</parent>
					<nodeName>DamageWeapon1</nodeName>
					<object>Damage</object>
					<value>50</value>
					<resourceCostType>Resource</resourceCostType>
					<resourceAmount>80</resourceAmount>
				</upgradeNode>
			</type>
		</tree>
	</upgrade>
	<resources src = "vooga.rts.gamedesign.sprite.gamesprites.Resource">
		<resource>
			<name>gold</name>
			<img>gold.png</img>
			<health>250</health>
		</resource>
		<resource>
			<name>wood</name>
			<img>wood.jpg</img>
			<health>250</health>
		</resource>
	</resources>
	<strategies>
		<attacks>
			<canattack src = "vooga.rts.gamedesign.strategy.attackstrategy.CanAttack"/>
			<cannotattack src = "vooga.rts.gamedesign.strategy.attackstrategy.CannotAttack"/>
		</attacks>
		<occupys>
			<canbeoccupied src = "vooga.rts.gamedesign.strategy.occupystrategy.CanBeOccupied"/>
			<cannotbeoccupied src = "vooga.rts.gamedesign.strategy.occupystrategy.CannotBeOccupied"/>
		</occupys>
		<gathers>
			<cangather src = "vooga.rts.gamedesign.strategy.gatherstrategy.CanGather"/>
			<cannotgather src = "vooga.rts.gamedesign.strategy.gatherstrategy.CannotGather"/>
		</gathers>
		<upgrades>
			<canupgrade src = "vooga.rts.gamedesign.strategy.upgradestrategy.CanUpgrade"/>
			<cannotupgrade src = "vooga.rts.gamedesign.strategy.upgradestrategy.CannotUpgrade"/>
		</upgrades>
	</strategies>
	<buildings src = "vooga.rts.gamedesign.sprite.gamesprites.interactive.buildings.Building">
		<building>
			<name>home</name>
			<img>images/castleHaha.gif</img>
			<sound>pikachu.wav</sound>
			<health>2000</health>
			<buildtime>10</buildtime>
			<occupy>cannotbeoccupied</occupy>
			<upgrade>canupgrade</upgrade>
			<upgradeTreeName>RegularUpgrade</upgradeTreeName>
			<produce>Marine</produce>
			<myweapons></myweapons>
			<information>
				<description>Welcome home</description>
				<button>buttons/marine.png</button>
				<cost>
					<gold>50</gold>
					<wood>10</wood>
				</cost>				
			</information>			
		</building>
		<building>
			<name>garrison</name>
			<img>images/garrisonHaha.gif</img>
			<sound>pikachu.wav</sound>
			<health>1000</health>
			<buildtime>5</buildtime>
			<occupy>canbeoccupied</occupy>
			<upgrade>cannotupgrade</upgrade>
			<upgradeTreeName></upgradeTreeName>
			<produce>Marine</produce>
			<myweapons></myweapons>
			<information>
				<description>I am a garrison</description>
				<button>buttons/marine.png</button>
				<cost>
					<gold>60</gold>
					<wood>30</wood>
				</cost>				
			</information>			
		</building>
		<custombuilding src = "vooga.rts.gamedesign.sprite.gamesprites.interactive.buildings.Tower">
			<name>tower</name>
		</custombuilding>
	</buildings>
	<units src = "vooga.rts.gamedesign.sprite.gamesprites.interactive.units.Unit">
		<unit>
			<name>Marine</name>
			<img>images/soldierHaha.gif</img>
			<sound>pikachu.wav</sound>
			<health>55</health>
			<buildtime>3</buildtime>
			<speed>180</speed>
			<gather>cannotgather</gather>
			<occupy>cannotbeoccupied</occupy>
			<upgrade>canupgrade</upgrade>
			<upgradeTreeName>SoldierUpgrade</upgradeTreeName>
			<produce>home</produce>
			<myweapons>gun</myweapons>
			<information>
				<description>I am a big doo doo</description>
				<button>buttons/marine.png</button>
				<cost>
					<gold>25</gold>
					<wood>2</wood>
				</cost>				
			</information>
		</unit>
		<unit>
			<name>worker</name>
			<img>images/workerHaha.gif</img>
			<sound>pikachu.wav</sound>
			<health>40</health>
			<buildtime>2</buildtime>
			<speed>160</speed>
			<gather>cangather</gather>
			<occupy>cannotbeoccupied</occupy>
			<upgrade>canupgrade</upgrade>
			<upgradeTreeName>RegularUpgrade</upgradeTreeName>
			<produce></produce>
			<myweapons></myweapons>
			<information>
				<description>I am a big doo doo</description>
				<button>images/scv.png</button>
				<cost>
					<gold>5</gold>
					<wood>1</wood>
				</cost>
			</information>			
		</unit>
	</units>
	<weapons src = "vooga.rts.gamedesign.weapon.Weapon">
			<weapon>
				<name>gun</name>
				<myprojectile>bullet</myprojectile>
				<range>200</range>
				<cooldown>2</cooldown>
			</weapon>
			<weapon>
				<name>sniper</name>
				<myprojectile>sniperbullet</myprojectile>
				<range>300</range>
				<cooldown>2</cooldown>
			</weapon>
	</weapons>
	<projectiles src = "vooga.rts.gamedesign.sprite.gamesprites.Projectile">
		<projectile>
			<name>bullet</name>
			<img>images/bullet.png</img>
			<damage>15</damage>
			<lifespan>120</lifespan>
			<speed>230</speed>
		</projectile>
		<projectile>
			<name>sniperbullet</name>
			<img>images/bullet.png</img>
			<damage>25</damage>
			<lifespan>150</lifespan>
			<speed>250</speed>
		</projectile>
	</projectiles>
</GameElements>